django_fsm/__init__.py
django_fsm_2/__init__.py
django_fsm_log/__init__.py
django_fsm_log/decorators.py
django_fsm_log/models.py
django_fsm_rx/__init__.py
django_fsm_rx/admin.py
django_fsm_rx/apps.py
django_fsm_rx/audit.py
django_fsm_rx/conf.py
django_fsm_rx/log.py
django_fsm_rx/migration.py
django_fsm_rx/models.py
django_fsm_rx/py.typed
django_fsm_rx/signals.py
django_fsm_rx/widgets.py
django_fsm_rx/contrib/__init__.py
django_fsm_rx/contrib/rules.py
django_fsm_rx/management/__init__.py
django_fsm_rx/management/commands/__init__.py
django_fsm_rx/management/commands/bump_version.py
django_fsm_rx/management/commands/check_fsm_migration.py
django_fsm_rx/management/commands/graph_transitions.py
django_fsm_rx/migrations/0001_initial.py
django_fsm_rx/migrations/0002_fsmtransitionlog_by_fsmtransitionlog_description.py
django_fsm_rx/migrations/0003_migrate_django_fsm_log_data.py
django_fsm_rx/migrations/__init__.py
django_fsm_rx/static/django_fsm_rx/css/cascade_widget.css
django_fsm_rx/static/django_fsm_rx/js/cascade_widget.js
django_fsm_rx/templates/django_fsm_rx/fsm_admin_change_form.html
django_fsm_rx/templates/django_fsm_rx/fsm_transition_form.html
django_fsm_rx/templates/django_fsm_rx/widgets/cascade_select.html
django_fsm_rx-5.1.8.dist-info/METADATA
django_fsm_rx-5.1.8.dist-info/WHEEL
django_fsm_rx-5.1.8.dist-info/licenses/LICENSE
django_fsm_rx-5.1.8.dist-info/RECORD
